<?xml version="1.0" encoding="ISO-8859-1" ?>

<lbatexts>
  <game>2</game>
  <quotes>
    <quote id="1" type="1">Mas... quem é você ?</quote>
    <quote id="2" type="1">Como você sabia que eu vinha aqui?</quote>
    <quote id="3" type="1">Ah, finalmente, aí está você ! Já estava achando que nÆo ia te ver hoje.</quote>
    <quote id="4" type="1">Eu sou um mercenário, meu filho. Um mercenário que Dark Monk pagou para te matar. Eu nÆo sei porque, mas ele tem muito medo de você !! No entanto... Você nÆo me parece tÆo assustador...</quote>
    <quote id="5" type="1">Meu filho, você é tÆo discreto quanto um monstro do gás. Quando você entrou em contato com Johnny Rocket, meus espiäes estavam lá. Desde entÆo te seguimos. Eu sabia que você desceria ao sub-gás. EntÆo resolvi te esperar aqui. Mas chega de papo. Agora, meu filho, prepare-se para morrer !!</quote>
  </quotes>
</lbatexts>
